milvus/__init__.py
milvus/settings.py
milvus/client/__init__.py
milvus/client/abstract.py
milvus/client/asynch.py
milvus/client/check.py
milvus/client/client_hooks.py
milvus/client/exceptions.py
milvus/client/grpc_handler.py
milvus/client/http_handler.py
milvus/client/pool.py
milvus/client/prepare.py
milvus/client/stub.py
milvus/client/types.py
milvus/client/utils.py
milvus/client/hooks/__init__.py
milvus/client/hooks/abstract.py
milvus/grpc_gen/__init__.py
milvus/grpc_gen/milvus_pb2.py
milvus/grpc_gen/milvus_pb2_grpc.py
milvus/grpc_gen/status_pb2.py
milvus/grpc_gen/status_pb2_grpc.py
pymilvus_test-1.0.0.dist-info/LICENSE
pymilvus_test-1.0.0.dist-info/METADATA
pymilvus_test-1.0.0.dist-info/WHEEL
pymilvus_test-1.0.0.dist-info/top_level.txt
pymilvus_test-1.0.0.dist-info/RECORD
