Metadata-Version: 2.1
Name: pymilvus-test
Version: 1.0.0
Summary: Python Sdk for Milvus
Home-page: https://github.com/milvus-io/pymilvus
License: Apache-2.0
Platform: UNKNOWN
Classifier: Programming Language :: Python :: 3.6
Classifier: Programming Language :: Python :: 3.7
Classifier: Programming Language :: Python :: 3.8
Requires-Python: >=3.6
Requires-Dist: grpcio (>=1.22.0)
Requires-Dist: grpcio-tools (>=1.22.0)
Requires-Dist: requests (>=2.22.0)
Requires-Dist: ujson (>=1.35)
Requires-Dist: numpy (>=1.16.3)
